great/__init__.py
great/_cli.py
great/config.py
great/extract.py
great/musicbrainz.py
great/tap.py
great/web.py
great/alembic/__init__.py
great/alembic/config.ini
great/alembic/env.py
great/alembic/script.py.mako
great/alembic/versions/44359856d0a6_initial_revision.py
great/alembic/versions/__init__.py
great/models/__init__.py
great/models/_guid.py
great/models/core.py
great/models/music.py
great/schemas/artist.json
great/tests/__init__.py
great/tests/integration/__init__.py
great/tests/integration/test_music.py
great/views/__init__.py
great/views/music.py
twisted/plugins/great.py
great-0.2.0.dist-info/COPYING
great-0.2.0.dist-info/METADATA
great-0.2.0.dist-info/WHEEL
great-0.2.0.dist-info/entry_points.txt
great-0.2.0.dist-info/top_level.txt
great-0.2.0.dist-info/RECORD
