Metadata-Version: 2.1
Name: great
Version: 0.2.0
Summary: "A ratings aggregator"
Home-page: https://github.com/Julian/Great
Author: Julian Berman
Author-email: Julian+Great@GrayVines.com
License: UNKNOWN
Platform: UNKNOWN
Classifier: Development Status :: 3 - Alpha
Classifier: Operating System :: OS Independent
Classifier: Programming Language :: Python
Classifier: Programming Language :: Python :: 2.7
Classifier: Programming Language :: Python :: 2
Classifier: Programming Language :: Python :: Implementation :: CPython
Classifier: Programming Language :: Python :: Implementation :: PyPy
Requires-Dist: Alchimia
Requires-Dist: alembic
Requires-Dist: appdirs
Requires-Dist: attrs
Requires-Dist: click
Requires-Dist: filesystems
Requires-Dist: hyperlink
Requires-Dist: Minion
Requires-Dist: SQLAlchemy
Requires-Dist: toml
Requires-Dist: Twisted
Requires-Dist: txmusicbrainz
